<?xml version="1.0" encoding="UTF-8"?>
<!DOCTYPE mapper PUBLIC "-//mybatis.org//DTD Mapper 3.0//EN" "http://mybatis.org/dtd/mybatis-3-mapper.dtd">
<mapper namespace="com.musicfire.modular.system.dao.RoleMapper">

    <!-- 通用查询映射结果 -->
    <resultMap id="BaseResultMap" type="com.musicfire.modular.system.entity.Role">
        <id column="id" property="id" />
        <result column="name" property="name" />
        <result column="flag" property="flag" />
        <result column="describe" property="describe" />
        <result column="create_time" property="createTime" />
        <result column="create_id" property="createId" />
        <result column="update_id" property="updateId" />
        <result column="update_time" property="updateTime" />
    </resultMap>

    <select id="queryByPage" resultMap="BaseResultMap" parameterType="com.musicfire.modular.system.query.RolePage">
        select * from sys_role where flag =false limit #{startPosition},#{pageSize}
    </select>
    <select id="countByPage" resultType="java.lang.Integer" parameterType="com.musicfire.modular.system.query.RolePage">
        select count(id) from sys_role where flag =false
    </select>
</mapper>
